coco_orm/__init__.py
coco_orm/collections/__init__.py
coco_orm/collections/annotation.py
coco_orm/collections/category.py
coco_orm/collections/core.py
coco_orm/collections/image.py
coco_orm/collections/image_repository.py
coco_orm/collections/license.py
coco_orm/collections/utils.py
coco_orm/dataset/core.py
coco_orm/dataset/utils.py
coco_orm/filters/__init__.py
coco_orm/filters/annotation.py
coco_orm/filters/category.py
coco_orm/filters/core.py
coco_orm/filters/expression.py
coco_orm/filters/image.py
coco_orm/filters/license.py
coco_orm/filters/properties.py
coco_orm/filters/utils.py
coco_orm/models/__init__.py
coco_orm/models/annotation.py
coco_orm/models/category.py
coco_orm/models/core.py
coco_orm/models/image.py
coco_orm/models/info.py
coco_orm/models/license.py
coco_orm/operators/__init__.py
coco_orm/operators/core.py
coco_orm-1.0.1.dist-info/LICENSE
coco_orm-1.0.1.dist-info/METADATA
coco_orm-1.0.1.dist-info/WHEEL
coco_orm-1.0.1.dist-info/top_level.txt
coco_orm-1.0.1.dist-info/RECORD
