Metadata-Version: 2.1
Name: coco_orm
Version: 1.0.1
Summary: An ORM built to simplify working with datasets in COCO format.
Author: Tarabon4ik
Project-URL: Homepage, https://github.com/Tarabon4ik/coco_orm
Project-URL: Issues, https://github.com/Tarabon4ik/coco_orm/issues
Classifier: Programming Language :: Python :: 3
Classifier: License :: OSI Approved :: MIT License
Classifier: Operating System :: OS Independent
Requires-Python: >=3.6
License-File: LICENSE
